{
    "id": "AZBEFB",
    "parent_bible_id": null,
    "uuid": "859c09eb-561d-4f37-ba2b-9b0ceabf03d2",
    "iso": "azb",
    "language": {
        "name": "South Azerbaijani"
    },
    "title": "Azerbaijani Bible 2008",
    "title_vernacular": "Azərbaycan Müqəddəs Kitab",
    "description": null,
    "description_short": null,
    "description_vernacular": null,
    "copyright": null,
    "copyright_type": null,
    "date": null,
    "country_id": "IR",
    "country": {
        "name": "Iran"
    },
    "alphabet": {
        "name": "Arabic",
        "script": "Arab",
        "fonts": []
    },
    "pod": [],
    "links": [
        {
            "url": "https://play.google.com/store/apps/details?id=org.fcbh.azbemv.n1.n&hl=en_US&gl=US",
            "title": "Full Bible",
            "scope": "",
            "type": "app",
            "filesize": "0",
            "provider": "Google Play",
            "publisher_id": "0a8fa4d7-e5c4-4933-8f49-dc633669d168",
            "publisher": "Google Play Store"
        }
    ],
    "publishers": [],
    "providers": [],
    "equivalents": [],
    "books": null
}