{
    "id": "ITALND",
    "parent_bible_id": null,
    "uuid": "cb7b4524-0163-4dd9-9443-628db6803550",
    "iso": "ita",
    "language": {
        "name": "Italian"
    },
    "title": "New Italian Standard Bible",
    "title_vernacular": "La Nuova Diodati",
    "description": null,
    "description_short": null,
    "description_vernacular": null,
    "copyright": "© 2014 Editrice Elledici, Torino – United Bible Societies/Società Biblica Britannica e Forestiera.",
    "copyright_type": null,
    "date": null,
    "country_id": "IT",
    "country": {
        "name": "Italy"
    },
    "alphabet": {
        "name": "Latin",
        "script": "Latn",
        "fonts": []
    },
    "pod": [],
    "links": [
        {
            "url": "http://amzn.to/1DsJ6vj",
            "title": "Pocket Size",
            "scope": "",
            "type": "print",
            "filesize": "0",
            "provider": "Amazon Marketplace",
            "publisher_id": null,
            "publisher": null
        },
        {
            "url": "http://amzn.to/1TOoEPc",
            "title": "Paperback",
            "scope": "",
            "type": "print",
            "filesize": "0",
            "provider": "Amazon Marketplace",
            "publisher_id": null,
            "publisher": null
        },
        {
            "url": "http://amzn.to/1g2k7u8",
            "title": "Full Bible",
            "scope": "",
            "type": "mobi",
            "filesize": "0",
            "provider": "Amazon Marketplace",
            "publisher_id": null,
            "publisher": null
        },
        {
            "url": "https://www.biblegateway.com/versions/La-Nuova-Diodati-LND/#booklist",
            "title": "Full Bible",
            "scope": "",
            "type": "web",
            "filesize": "0",
            "provider": "BibleGateway",
            "publisher_id": "9696ef31-b54c-4a20-82ab-f1b8a527e48a",
            "publisher": "Bible Gateway"
        },
        {
            "url": "https://www.biblegateway.com/versions/index.php?action=getVersionInfo&vid=55&lang=53",
            "title": "La Nuova Diodati",
            "scope": "",
            "type": "web",
            "filesize": "0",
            "provider": "Bible Gateway",
            "publisher_id": "9696ef31-b54c-4a20-82ab-f1b8a527e48a",
            "publisher": "Bible Gateway"
        },
        {
            "url": "https://www.bible.com/versions/1196-icl00d-traduzione-interconfessionale-in-lingua-corrente",
            "title": "Traduzione Interconfessionale in Lingua Corrente",
            "scope": "",
            "type": "web",
            "filesize": "0",
            "provider": "ItalyBFBS",
            "publisher_id": "a4f1fc26-64a5-412f-804d-d91da40aee72",
            "publisher": "YouVersion"
        },
        {
            "url": "https://bible.com/versions/1196",
            "title": "Youversion",
            "scope": "",
            "type": "",
            "filesize": "0",
            "provider": "",
            "publisher_id": "a4f1fc26-64a5-412f-804d-d91da40aee72",
            "publisher": "YouVersion"
        }
    ],
    "publishers": [],
    "providers": [],
    "equivalents": [
        {
            "organization_id": "a4f1fc26-64a5-412f-804d-d91da40aee72",
            "equivalent_id": "1196",
            "site": "",
            "suffix": "",
            "type": "",
            "url": "https://bible.com/versions/1196"
        }
    ],
    "books": null
}