{
    "id": "NOITLF",
    "parent_bible_id": null,
    "uuid": "248e1027-9cfc-460d-85ad-21aabcb36025",
    "iso": "noi",
    "language": {
        "name": "Noiri"
    },
    "title": "Noiri Bible",
    "title_vernacular": "नोयरी नोवलू नियम",
    "description": null,
    "description_short": null,
    "description_vernacular": null,
    "copyright": "℗ Noiri New Testament, CC-BY-SA-4.0, Davar Partners International, The Love Fellowship, 2023",
    "copyright_type": null,
    "date": null,
    "country_id": "IN",
    "country": {
        "name": "India"
    },
    "alphabet": {
        "name": "Devanagari (Nagari)",
        "script": "Deva",
        "fonts": []
    },
    "pod": [],
    "links": [],
    "publishers": [],
    "providers": [],
    "equivalents": [
        {
            "organization_id": null,
            "equivalent_id": "9e2f733cd93f5638",
            "site": null,
            "suffix": "DBL",
            "type": "DBL",
            "url": null
        }
    ],
    "books": null
}