{
    "id": "RUPVAM",
    "parent_bible_id": "",
    "uuid": "82300619-0a83-4fb9-a179-2cc182d98324",
    "iso": "rup",
    "language": {
        "name": "Macedo-Romanian"
    },
    "title": "Aromanian Gospel of Matthew",
    "title_vernacular": "Vangheilu al Mattheu",
    "description": null,
    "description_short": null,
    "description_vernacular": null,
    "copyright": "Public Domain",
    "copyright_type": "OPEN",
    "date": null,
    "country_id": "MK",
    "country": {
        "name": "North Macedonia"
    },
    "alphabet": {
        "name": "Latin",
        "script": "Latn",
        "fonts": []
    },
    "pod": [
        {
            "publisher_id": "d3950ccc-dc18-4e63-92c2-a0f5e2eef6ac",
            "partner_id": null,
            "description": "This Bible is in the Public Domain and is produced at cost by the Digital Bible Society (dbs.org).<br /><br />This Bible, and many others, are available for free download in a variety of digital formats at dbs.org/bibles.",
            "trim": "us_letter",
            "scope": "bible",
            "pages": 31,
            "print_ready": 0,
            "print_banned": 0
        },
        {
            "publisher_id": "d3950ccc-dc18-4e63-92c2-a0f5e2eef6ac",
            "partner_id": null,
            "description": "This Bible is in the Public Domain and is produced at cost by the Digital Bible Society (dbs.org).<br /><br />This Bible, and many others, are available for free download in a variety of digital formats at dbs.org/bibles.",
            "trim": "us_trade",
            "scope": "bible",
            "pages": 44,
            "print_ready": 0,
            "print_banned": 0
        }
    ],
    "links": [
        {
            "url": "https://www.bible.com/versions/1655",
            "title": "Youversion",
            "scope": "",
            "type": "web",
            "filesize": "0",
            "provider": "Bible.com",
            "publisher_id": "a4f1fc26-64a5-412f-804d-d91da40aee72",
            "publisher": "YouVersion"
        },
        {
            "url": "https://www.bible.com/versions/1655-arom-vangheilu-al-matheu-1889",
            "title": "Vangheilu al Matheu 1889",
            "scope": "",
            "type": "web",
            "filesize": "0",
            "provider": "British &amp; Foreign Bible Society",
            "publisher_id": "a4f1fc26-64a5-412f-804d-d91da40aee72",
            "publisher": "YouVersion"
        },
        {
            "url": "https://app.thedigitalbiblelibrary.org/entry?id=ffffb04c2faa49da",
            "title": "Bible For Developers",
            "scope": "P",
            "type": "archive",
            "filesize": "0",
            "provider": "Digital Bible Library",
            "publisher_id": "f4b27cf8-7dbf-4bfb-8cd4-93315e272e2a",
            "publisher": "The Digital Bible Library"
        },
        {
            "url": "https://bible.com/versions/1655",
            "title": "Youversion",
            "scope": "",
            "type": "",
            "filesize": "0",
            "provider": "",
            "publisher_id": "a4f1fc26-64a5-412f-804d-d91da40aee72",
            "publisher": "YouVersion"
        },
        {
            "url": "https://dbs.org/bibles/RUPVAM",
            "title": "eBook Downloads",
            "scope": null,
            "type": null,
            "filesize": null,
            "provider": null,
            "publisher_id": "93619ca8-7f05-48dc-995c-6f46cdc94918",
            "publisher": "Digital Bible Society"
        }
    ],
    "publishers": [],
    "providers": [],
    "equivalents": [
        {
            "organization_id": "f4b27cf8-7dbf-4bfb-8cd4-93315e272e2a",
            "equivalent_id": "ffffb04c2faa49da",
            "site": "",
            "suffix": "",
            "type": "DBL",
            "url": "https://app.thedigitalbiblelibrary.org/entry?id=ffffb04c2faa49da"
        },
        {
            "organization_id": "a4f1fc26-64a5-412f-804d-d91da40aee72",
            "equivalent_id": "1655",
            "site": "",
            "suffix": "",
            "type": "",
            "url": "https://bible.com/versions/1655"
        }
    ],
    "books": null
}