{
    "id": "TPXMEPH",
    "parent_bible_id": "",
    "uuid": "43250e85-8d07-4d87-b37b-24d6db889944",
    "iso": "tpx",
    "language": {
        "name": "Acatepec Me'phaa"
    },
    "title": "Meꞌphaa de Teocuitlapa Bible Portions",
    "title_vernacular": "I̱yu̱u̱ꞌ Páblúꞌ dí nijka̱ inúú",
    "description": "Me'paa, Me'phàà, Tlapaneco, Me’phaa de Teocuitlapa, Me'phaa Xma’íín, Me’phaa de Zoquitlán, Me’phaa del Noroeste Bajo, Me’phaa de Platanillo, Mepaa Bible Portions",
    "description_short": "",
    "description_vernacular": "",
    "copyright": "© 2022 Wycliffe Bible Translators, Inc.",
    "copyright_type": "",
    "date": null,
    "country_id": "MX",
    "country": {
        "name": "Mexico"
    },
    "alphabet": {
        "name": "Latin",
        "script": "Latn",
        "fonts": []
    },
    "pod": [],
    "links": [],
    "publishers": [],
    "providers": [],
    "equivalents": [],
    "books": null
}