{
  "pk": 1428,
  "hid": "bfr",
  "father_pk": 280,
  "family_pk": 280,
  "level": "language",
  "bookkeeping": false,
  "category": "Unclassifiable",
  "newick": "'Bazigar [bazi1237][bfr]-l-':1",
  "child_family_count": 0,
  "child_language_count": 0,
  "child_dialect_count": 0,
  "macroareas": {},
  "jsondata": {
    "iso_retirement": null,
    "ethnologue_comment": null,
    "links": [
      {
        "url": "https://www.wikidata.org/entity/Q8829558",
        "label": null
      },
      {
        "url": "https://en.wikipedia.org/wiki/Bazigar_language",
        "label": null
      }
    ],
    "meds": [
      [
        "146225",
        "wordlist_or_less",
        1883,
        173,
        "Denzil Ibbetson 1916 [1883]"
      ]
    ]
  },
  "id": "bazi1237",
  "name": "Bazigar",
  "description": null,
  "markup_description": null,
  "latitude": 25.2977,
  "longitude": 77.2213,
  "classification": [
    {
      "name": "Unclassifiable",
      "id": "uncl1493",
      "url": "https://glottolog.org/resource/languoid/id/uncl1493"
    }
  ],
  "iso639-3": "bfr"
}