{
  "pk": 8978,
  "hid": "hbn",
  "father_pk": 6484,
  "family_pk": 254,
  "level": "language",
  "bookkeeping": false,
  "category": "Spoken L1 Language",
  "newick": "'Ebang [heib1243][hbn]-l-':1",
  "child_family_count": 0,
  "child_language_count": 0,
  "child_dialect_count": 0,
  "macroareas": {},
  "jsondata": {
    "iso_retirement": null,
    "ethnologue_comment": null,
    "links": [
      {
        "url": "https://www.wikidata.org/entity/Q35523",
        "label": null
      },
      {
        "url": "https://en.wikipedia.org/wiki/Heiban_language",
        "label": null
      },
      {
        "url": "https://phoible.org/languages/heib1243",
        "label": null
      }
    ],
    "meds": [
      [
        "62934",
        "grammar_sketch",
        1943,
        37,
        "Meinhof, Carl 1943-1944"
      ],
      [
        "98616",
        "grammar_sketch",
        1928,
        0,
        "Phoebe MacDiarmid 1928"
      ],
      [
        "62171",
        "wordlist_or_less",
        1925,
        0,
        "MacDiarmid, Phoebe Ann and MacDiarmid, Donald Neil 1925"
      ],
      [
        "97645",
        "wordlist_or_less",
        1921,
        0,
        "MacDiarmid, Donald Neil 1921"
      ],
      [
        "68370",
        "wordlist_or_less",
        1914,
        0,
        "MacDiarmid, Donald Neil 1914"
      ]
    ]
  },
  "id": "heib1243",
  "name": "Ebang",
  "description": null,
  "markup_description": null,
  "latitude": 11.2908,
  "longitude": 30.5282,
  "classification": [
    {
      "name": "Heibanic",
      "id": "heib1242",
      "url": "https://glottolog.org/resource/languoid/id/heib1242"
    },
    {
      "name": "West-Central Heibanic",
      "id": "west2502",
      "url": "https://glottolog.org/resource/languoid/id/west2502"
    },
    {
      "name": "Central Heibanic",
      "id": "cent2049",
      "url": "https://glottolog.org/resource/languoid/id/cent2049"
    },
    {
      "name": "Ebang-Logol",
      "id": "eban1241",
      "url": "https://glottolog.org/resource/languoid/id/eban1241"
    },
    {
      "name": "Ebang-Laru",
      "id": "eban1242",
      "url": "https://glottolog.org/resource/languoid/id/eban1242"
    }
  ],
  "iso639-3": "hbn"
}