{
  "pk": 21941,
  "hid": "piw",
  "father_pk": 20197,
  "family_pk": 320,
  "level": "language",
  "bookkeeping": false,
  "category": "Spoken L1 Language",
  "newick": "'Pimbwe [pimb1238][piw]-l-':1",
  "child_family_count": 0,
  "child_language_count": 0,
  "child_dialect_count": 0,
  "macroareas": {},
  "jsondata": {
    "iso_retirement": null,
    "ethnologue_comment": null,
    "links": [
      {
        "url": "https://endangeredlanguages.com/lang/5072",
        "label": "Pimbwe"
      },
      {
        "url": "https://www.wikidata.org/entity/Q3894132",
        "label": null
      },
      {
        "url": "https://en.wikipedia.org/wiki/Pimbwe_language",
        "label": null
      }
    ],
    "meds": [
      [
        "590040",
        "grammar_sketch",
        2020,
        125,
        "Jonathan Weiss 2020"
      ],
      [
        "72854",
        "phonology_or_text",
        1975,
        0,
        "Chomba, D.S. 1975"
      ],
      [
        "662287",
        "wordlist_or_less",
        1971,
        56,
        "Guthrie, Malcolm 1971"
      ],
      [
        "39378",
        "wordlist_or_less",
        1947,
        1,
        "Greenway, P.J. 1947"
      ],
      [
        "663436",
        "wordlist_or_less",
        1919,
        0,
        "Johnston, Harry Hamilton 1919/22"
      ],
      [
        "26011",
        "wordlist_or_less",
        1913,
        6,
        "Molitor, P.H. 1913"
      ]
    ]
  },
  "id": "pimb1238",
  "name": "Pimbwe",
  "description": null,
  "markup_description": null,
  "latitude": -6.81358,
  "longitude": 31.4289,
  "classification": [
    {
      "name": "Atlantic-Congo",
      "id": "atla1278",
      "url": "https://glottolog.org/resource/languoid/id/atla1278"
    },
    {
      "name": "Volta-Congo",
      "id": "volt1241",
      "url": "https://glottolog.org/resource/languoid/id/volt1241"
    },
    {
      "name": "Benue-Congo",
      "id": "benu1247",
      "url": "https://glottolog.org/resource/languoid/id/benu1247"
    },
    {
      "name": "Bantoid",
      "id": "bant1294",
      "url": "https://glottolog.org/resource/languoid/id/bant1294"
    },
    {
      "name": "Southern Bantoid",
      "id": "sout3152",
      "url": "https://glottolog.org/resource/languoid/id/sout3152"
    },
    {
      "name": "Narrow Bantu",
      "id": "narr1281",
      "url": "https://glottolog.org/resource/languoid/id/narr1281"
    },
    {
      "name": "East Bantu",
      "id": "east2731",
      "url": "https://glottolog.org/resource/languoid/id/east2731"
    },
    {
      "name": "Corridor Bantu",
      "id": "corr1234",
      "url": "https://glottolog.org/resource/languoid/id/corr1234"
    },
    {
      "name": "Mbozi",
      "id": "mboz1235",
      "url": "https://glottolog.org/resource/languoid/id/mboz1235"
    },
    {
      "name": "Mwika",
      "id": "mwik1240",
      "url": "https://glottolog.org/resource/languoid/id/mwik1240"
    }
  ],
  "iso639-3": "piw"
}