{
  "pk": 15355,
  "hid": "vbb",
  "father_pk": 12568,
  "family_pk": 289,
  "level": "language",
  "bookkeeping": false,
  "category": "Spoken L1 Language",
  "newick": "'Southeast Babar [sout2883][vbb]-l-':1",
  "child_family_count": 0,
  "child_language_count": 0,
  "child_dialect_count": 0,
  "macroareas": {},
  "jsondata": {
    "iso_retirement": null,
    "ethnologue_comment": null,
    "links": [
      {
        "url": "https://www.wikidata.org/entity/Q12952247",
        "label": null
      },
      {
        "url": "https://en.wikipedia.org/wiki/Southeast_Babar_language",
        "label": null
      }
    ],
    "meds": [
      [
        "319122",
        "phonology_or_text",
        2009,
        8,
        "Hein Steinhauer 2009"
      ],
      [
        "110693",
        "wordlist_or_less",
        1993,
        1,
        "Mark Taber 1993"
      ]
    ]
  },
  "id": "sout2883",
  "name": "Southeast Babar",
  "description": null,
  "markup_description": null,
  "latitude": -7.94359,
  "longitude": 129.8,
  "classification": [
    {
      "name": "Austronesian",
      "id": "aust1307",
      "url": "https://glottolog.org/resource/languoid/id/aust1307"
    },
    {
      "name": "Malayo-Polynesian",
      "id": "mala1545",
      "url": "https://glottolog.org/resource/languoid/id/mala1545"
    },
    {
      "name": "Timor-Babar",
      "id": "timo1265",
      "url": "https://glottolog.org/resource/languoid/id/timo1265"
    },
    {
      "name": "Southwest Maluku",
      "id": "sout3382",
      "url": "https://glottolog.org/resource/languoid/id/sout3382"
    },
    {
      "name": "Babar",
      "id": "baba1274",
      "url": "https://glottolog.org/resource/languoid/id/baba1274"
    },
    {
      "name": "South Babar",
      "id": "sout2881",
      "url": "https://glottolog.org/resource/languoid/id/sout2881"
    },
    {
      "name": "Masela-South Babar",
      "id": "mase1249",
      "url": "https://glottolog.org/resource/languoid/id/mase1249"
    }
  ],
  "iso639-3": "vbb"
}