{
  "pk": 303,
  "hid": "auc",
  "father_pk": null,
  "family_pk": null,
  "level": "language",
  "bookkeeping": false,
  "category": "Spoken L1 Language",
  "newick": "'Waorani [waor1240][auc]-l-':1",
  "child_family_count": 0,
  "child_language_count": 0,
  "child_dialect_count": 0,
  "macroareas": {},
  "jsondata": {
    "iso_retirement": null,
    "ethnologue_comment": null,
    "links": [
      {
        "url": "https://endangeredlanguages.com/lang/2065",
        "label": "Waorani"
      },
      {
        "url": "https://wals.info/languoid/lect/wals_code_wao",
        "label": "Waorani"
      },
      {
        "url": "https://en.wikipedia.org/wiki/Waorani_language",
        "label": null
      },
      {
        "url": "https://phoible.org/languages/waor1240",
        "label": null
      },
      {
        "url": "https://www.wikidata.org/entity/Q758570",
        "label": null
      }
    ],
    "meds": [
      [
        "79585",
        "grammar",
        1979,
        126,
        "Peeke, M. Catherine 1979"
      ],
      [
        "43958",
        "grammar_sketch",
        1968,
        252,
        "Peeke, M. Catherine 1968"
      ],
      [
        "129731",
        "phonology_or_text",
        1962,
        0,
        "Peeke, M. Catherine 1962"
      ],
      [
        "113075",
        "phonology_or_text",
        1959,
        14,
        "Saint, Rachel and Pike, Kenneth L. 1959"
      ],
      [
        "150556",
        "wordlist_or_less",
        1949,
        134,
        "Blomberg, Rolf 1949"
      ],
      [
        "34227",
        "wordlist_or_less",
        1930,
        6,
        "Günter Tessmann 1930"
      ]
    ]
  },
  "id": "waor1240",
  "name": "Waorani",
  "description": null,
  "markup_description": null,
  "latitude": -1.12312,
  "longitude": -76.683,
  "classification": [],
  "iso639-3": "auc"
}